cmdnote/__init__.py
cmdnote/argument_parser.py
cmdnote/cmdnote.py
cmdnote/command_parser.py
cmdnote/config.py
cmdnote/const.py
cmdnote/exception.py
cmdnote/main.py
cmdnote/notebook.py
cmdnote/store.py
cmdnote/ui.py
cmdnote/shell/__init__.py
cmdnote/shell/bash.py
cmdnote/shell/generic.py
cmdnote/system/__init__.py
cmdnote/system/unix.py
tests/__init__.py
tests/test_cmdnote.py
tests/test_main.py
tests/utils.py
cmdnote-0.1.0.dist-info/LICENSE
cmdnote-0.1.0.dist-info/METADATA
cmdnote-0.1.0.dist-info/WHEEL
cmdnote-0.1.0.dist-info/entry_points.txt
cmdnote-0.1.0.dist-info/top_level.txt
cmdnote-0.1.0.dist-info/RECORD
