Metadata-Version: 2.1
Name: cmdnote
Version: 0.1.0
Summary: Command line tool which stores your future commands
Home-page: https://github.com/zianke/cmdnote
Author: Zian Ke
Author-email: zian.ke@zian.ke
License: UNKNOWN
Platform: UNKNOWN
Classifier: Programming Language :: Python :: 3
Classifier: License :: OSI Approved :: MIT License
Classifier: Operating System :: OS Independent
Requires-Python: >=3.5
Requires-Dist: colorama
